hankel/__init__.py
hankel/_version.py
hankel/hankel.py
hankel/tools.py
hankel-1.2.2.dist-info/LICENSE.rst
hankel-1.2.2.dist-info/METADATA
hankel-1.2.2.dist-info/WHEEL
hankel-1.2.2.dist-info/top_level.txt
hankel-1.2.2.dist-info/RECORD
