Metadata-Version: 2.1
Name: hankel
Version: 1.2.2
Summary: Hankel Transformations using method of Ogata 2005
Home-page: https://github.com/steven-murray/hankel
Author: Steven Murray
Author-email: steven.g.murray@asu.edu
License: MIT
Project-URL: Documentation, https://hankel.readthedocs.io
Project-URL: Source, https://github.com/steven-murray/hankel
Project-URL: Tracker, https://github.com/steven-murray/hankel/issues
Project-URL: Changelog, https://github.com/steven-murray/hankel/blob/master/CHANGELOG.rst
Project-URL: Conda-Forge, https://anaconda.org/conda-forge/hankel
Classifier: Development Status :: 5 - Production/Stable
Classifier: Intended Audience :: Developers
Classifier: Intended Audience :: End Users/Desktop
Classifier: Intended Audience :: Science/Research
Classifier: License :: OSI Approved :: MIT License
Classifier: Natural Language :: English
Classifier: Operating System :: Unix
Classifier: Programming Language :: Python
Classifier: Programming Language :: Python :: 3
Classifier: Programming Language :: Python :: 3 :: Only
Classifier: Topic :: Scientific/Engineering
Classifier: Topic :: Utilities
Requires-Python: >=3.6
Provides-Extra: dev
Provides-Extra: docs
Provides-Extra: tests
License-File: LICENSE.rst
